AUTHORS.rst
HISTORY.rst
LICENSE
MANIFEST.in
README.rst
setup.cfg
setup.py
docs/Makefile
docs/astar.rst
docs/authors.rst
docs/bim.rst
docs/conf.py
docs/history.rst
docs/index.rst
docs/installation.rst
docs/license.rst
docs/make.bat
docs/modules.rst
docs/polygon.rst
docs/readme.rst
docs/references.rst
docs/slices.rst
docs/slipsurface.rst
docs/slope.rst
docs/slopestabl.rst
docs/smoothcurve.rst
docs/tools.rst
docs/usage.rst
docs/watertable.rst
pybimstab/__init__.py
pybimstab/astar.py
pybimstab/bim.py
pybimstab/polygon.py
pybimstab/slices.py
pybimstab/slipsurface.py
pybimstab/slope.py
pybimstab/slopestabl.py
pybimstab/smoothcurve.py
pybimstab/tools.py
pybimstab/watertable.py
pybimstab.egg-info/PKG-INFO
pybimstab.egg-info/SOURCES.txt
pybimstab.egg-info/dependency_links.txt
pybimstab.egg-info/entry_points.txt
pybimstab.egg-info/not-zip-safe
pybimstab.egg-info/requires.txt
pybimstab.egg-info/top_level.txt
tests/test_pybimstab.py