Metadata-Version: 1.1
Name: pybimstab
Version: 0.1.3
Summary: Application software to evaluate the stability of slopes made of Blocks-In-Matrix materials
Home-page: https://github.com/eamontoyaa/pybimstab
Author: Exneyder A. Montoya-Araque & Ludger O. Suarez-Burgoa
Author-email: eamontoyaa@gmail.com
License: BSD 2-Clause License
Keywords: slope stability,GLE,bimsoil,bimrock,tortuosity,A-star,Python,application software
Platform: UNKNOWN
Classifier: Development Status :: 2 - Pre-Alpha
Classifier: Intended Audience :: Science/Research
Classifier: Intended Audience :: Education
Classifier: License :: OSI Approved :: BSD License
Classifier: Natural Language :: English
Classifier: Programming Language :: Python :: 3.6
Classifier: Topic :: Scientific/Engineering
Classifier: Topic :: Scientific/Engineering :: Mathematics
